nbtui/__init__.py
nbtui/__main__.py
nbtui/cells.py
nbtui/display.py
nbtui/parser.py
nbtui/user_input.py
nbtui-0.0.3.dist-info/LICENSE
nbtui-0.0.3.dist-info/METADATA
nbtui-0.0.3.dist-info/WHEEL
nbtui-0.0.3.dist-info/entry_points.txt
nbtui-0.0.3.dist-info/top_level.txt
nbtui-0.0.3.dist-info/RECORD
