Metadata-Version: 2.1
Name: nbtui
Version: 0.0.3
Summary: View jupyter notebooks (with images) from the command line
Home-page: https://github.com/chentau/nbtui
Author: Tony Chen
Author-email: tchen1998@gmail.com
License: UNKNOWN
Platform: UNKNOWN
Requires-Python: >=3.6
License-File: LICENSE
Requires-Dist: bleach (==3.3.0)
Requires-Dist: build (==0.3.0)
Requires-Dist: certifi (==2020.12.5)
Requires-Dist: cffi (==1.14.5)
Requires-Dist: chardet (==4.0.0)
Requires-Dist: colorama (==0.4.4)
Requires-Dist: commonmark (==0.9.1)
Requires-Dist: cryptography (==3.4.6)
Requires-Dist: docutils (==0.16)
Requires-Dist: idna (==2.10)
Requires-Dist: jeepney (==0.6.0)
Requires-Dist: keyring (==22.0.1)
Requires-Dist: pep517 (==0.9.1)
Requires-Dist: Pillow (>=8.2.0)
Requires-Dist: pkginfo (==1.7.0)
Requires-Dist: pluggy (==0.12.0)
Requires-Dist: pycparser (==2.20)
Requires-Dist: Pygments (==2.8.0)
Requires-Dist: pytest (==6.2.2)
Requires-Dist: readme-renderer (==29.0)
Requires-Dist: requests (==2.25.1)
Requires-Dist: requests-toolbelt (==0.9.1)
Requires-Dist: rfc3986 (==1.4.0)
Requires-Dist: rich (==9.11.1)
Requires-Dist: SecretStorage (==3.3.1)
Requires-Dist: toml (==0.10.2)
Requires-Dist: tqdm (==4.57.0)
Requires-Dist: twine (==3.3.0)
Requires-Dist: typing-extensions (==3.7.4.3)
Requires-Dist: urllib3 (==1.26.3)
Requires-Dist: watchgod (==0.7)
Requires-Dist: webencodings (==0.5.1)
